imml/__init__.py
imml/ampute/__init__.py
imml/ampute/amputer.py
imml/ampute/remove_mods.py
imml/classify/__init__.py
imml/classify/m3care.py
imml/classify/map.py
imml/classify/muse.py
imml/classify/ragpt.py
imml/classify/_m3care/__init__.py
imml/classify/_m3care/graph_convolution.py
imml/classify/_m3care/mm_transformer_encoder.py
imml/classify/_m3care/nmt.py
imml/classify/_m3care/utils.py
imml/classify/_muse/__init__.py
imml/classify/_muse/code_encoder.py
imml/classify/_muse/ffn_encoder.py
imml/classify/_muse/gnn.py
imml/classify/_muse/rnn_encoder.py
imml/classify/_muse/text_encoder.py
imml/classify/_ragpt/__init__.py
imml/classify/_ragpt/core_tools.py
imml/classify/_ragpt/modules.py
imml/classify/_ragpt/vilt/__init__.py
imml/classify/_ragpt/vilt/configuration_vilt.py
imml/classify/_ragpt/vilt/image_processing_vilt.py
imml/classify/_ragpt/vilt/modeling_vilt.py
imml/cluster/__init__.py
imml/cluster/daimc.py
imml/cluster/eeimvc.py
imml/cluster/imscagl.py
imml/cluster/imsr.py
imml/cluster/integrao.py
imml/cluster/lfimvc.py
imml/cluster/mkkmik.py
imml/cluster/monet.py
imml/cluster/mrgcn.py
imml/cluster/nemo.py
imml/cluster/omvc.py
imml/cluster/opimc.py
imml/cluster/oslfimvc.py
imml/cluster/pimvc.py
imml/cluster/simcadc.py
imml/cluster/sumo.py
imml/cluster/_daimc/DAIMC.m
imml/cluster/_daimc/UpdateV_DAIMC.m
imml/cluster/_daimc/__init__.py
imml/cluster/_daimc/litekmeans.m
imml/cluster/_daimc/newinit.m
imml/cluster/_eeimvc/__init__.py
imml/cluster/_eeimvc/algorithm2.m
imml/cluster/_eeimvc/incompleteLateFusionMKCOrthHp_lambda.m
imml/cluster/_eeimvc/myInitializationHp.m
imml/cluster/_eeimvc/mycombFun.m
imml/cluster/_eeimvc/mykernelkmeans.m
imml/cluster/_eeimvc/updateBetaAbsentClustering.m
imml/cluster/_eeimvc/updateHPabsentClusteringOrthHp.m
imml/cluster/_eeimvc/updateWPabsentClusteringV1.m
imml/cluster/_imscagl/EProjSimplex_new.m
imml/cluster/_imscagl/EuDist2.m
imml/cluster/_imscagl/IMSAGL.m
imml/cluster/_imscagl/IMSC.m
imml/cluster/_imscagl/L2_distance_1.m
imml-0.2.0.dist-info/METADATA
imml-0.2.0.dist-info/WHEEL
imml-0.2.0.dist-info/top_level.txt
imml-0.2.0.dist-info/RECORD
