Metadata-Version: 2.1
Name: imml
Version: 0.2.0
Summary: A python package for multi-modal learning with incomplete data
Author-email: Alberto López <a.l.sanchez@medisin.uio.no>
Maintainer-email: Alberto López <a.l.sanchez@medisin.uio.no>
License: BSD 3-Clause License
Project-URL: Documentation, https://imml.readthedocs.io
Project-URL: Source, https://github.com/ocbe-uio/imml
Project-URL: Download, https://pypi.org/project/imml/#files
Project-URL: Tracker, https://github.com/ocbe-uio/imml/issues
Project-URL: Changelog, https://imml.readthedocs.io/stable/development/changelog.html
Keywords: multi-modal learning,machine learning,incomplete data,missing data
Classifier: Intended Audience :: Science/Research
Classifier: Intended Audience :: Developers
Classifier: Development Status :: 3 - Alpha
Classifier: License :: OSI Approved :: BSD License
Classifier: Operating System :: Microsoft :: Windows
Classifier: Operating System :: POSIX
Classifier: Operating System :: Unix
Classifier: Operating System :: MacOS
Classifier: Topic :: Software Development
Classifier: Topic :: Scientific/Engineering
Classifier: Programming Language :: Python :: 3
Classifier: Programming Language :: Python :: 3.10
Classifier: Programming Language :: Python :: 3.11
Classifier: Programming Language :: Python :: 3.12
Classifier: Programming Language :: Python :: 3.13
Requires-Python: >=3.10
Requires-Dist: scikit-learn>=1.4.1
Requires-Dist: pandas>=2.2.2
Requires-Dist: networkx>=2.5
Requires-Dist: h5py>=3.9.0
Requires-Dist: snfpy>=0
Requires-Dist: control>=0.10.1
Requires-Dist: cvxpy>=1.7.1
Provides-Extra: deep
Requires-Dist: lightning>=2.2; extra == "deep"
Requires-Dist: transformers>=4.51.3; extra == "deep"
Requires-Dist: torch-geometric>=2.6.1; extra == "deep"
Requires-Dist: torchvision>=0.19.1; extra == "deep"
Provides-Extra: docs
Requires-Dist: lightning>=2.2; extra == "docs"
Requires-Dist: transformers>=4.51.3; extra == "docs"
Requires-Dist: ipython<9.0.0,>=8.20.0; extra == "docs"
Requires-Dist: datasets==3.6.0; extra == "docs"
Requires-Dist: rpy2>=3.5.14; extra == "docs"
Requires-Dist: sphinx>=7.0.0; extra == "docs"
Requires-Dist: sphinx-gallery>=0.17.1; extra == "docs"
Requires-Dist: sphinx-rtd-theme>=1.0.0; extra == "docs"
Provides-Extra: matlab
Requires-Dist: ipython<9.0.0,>=8.20.0; extra == "matlab"
Requires-Dist: oct2py>=5.8.0; extra == "matlab"
Provides-Extra: r
Requires-Dist: rpy2>=3.5.14; extra == "r"
Provides-Extra: tests
Requires-Dist: pytest>=7.1.2; extra == "tests"
Requires-Dist: pytest-cov>=2.9.0; extra == "tests"
